{
"type": "FeatureCollection",
"name": "Slide2_FCreek",
"crs": { "type": "name", "properties": { "name": "urn:ogc:def:crs:OGC:1.3:CRS84" } },
"features": [
{ "type": "Feature", "properties": { "Id": 0 }, "geometry": { "type": "Point", "coordinates": [ -104.75456165390608, 38.747733590789935 ] } }
]
}
